README.md
setup.py
forests/__init__.py
forests.egg-info/PKG-INFO
forests.egg-info/SOURCES.txt
forests.egg-info/dependency_links.txt
forests.egg-info/not-zip-safe
forests.egg-info/requires.txt
forests.egg-info/top_level.txt