Metadata-Version: 1.0
Name: forests
Version: 0.0
Summary: Variations on Random Forests for classification / regression
Home-page: http://gitlab.com/theSage21/forests
Author: Arjoonn Sharma
Author-email: arjoonn.94@gmail.com
License: UNKNOWN
Keywords: forests,random forests,decision stream,decision jungle
Platform: UNKNOWN
